mcp_vademecum/__init__.py
mcp_vademecum/__main__.py
mcp_vademecum/server.py
mcp_vademecum-0.1.6.dist-info/METADATA
mcp_vademecum-0.1.6.dist-info/WHEEL
mcp_vademecum-0.1.6.dist-info/entry_points.txt
mcp_vademecum-0.1.6.dist-info/RECORD
