Metadata-Version: 2.4
Name: mcp-vademecum
Version: 0.1.6
Summary: MCP Server for Vademecum
Requires-Python: >=3.10
Requires-Dist: mcp[cli]>=1.2.0
Requires-Dist: requests>=2.28.1
